whisper_speaker_id/__init__.py
whisper_speaker_id/wsi.py
whisper_speaker_id-1.1.0.dist-info/LICENSE
whisper_speaker_id-1.1.0.dist-info/METADATA
whisper_speaker_id-1.1.0.dist-info/WHEEL
whisper_speaker_id-1.1.0.dist-info/top_level.txt
whisper_speaker_id-1.1.0.dist-info/RECORD
