Metadata-Version: 2.1
Name: whisper-speaker-id
Version: 1.1.0
Summary: Whisper Speaker Identification: A Python library for multiligual speaker identification and speaker embedding generation.
Home-page: https://github.com/jakariaemon/WSI
Author: Jakaria Emon
Author-email: jakariaemon1521@gmail.com
License: CC BY-NC-SA 4.0
Classifier: Programming Language :: Python :: 3
Classifier: License :: Other/Proprietary License
Classifier: Operating System :: OS Independent
Requires-Python: >=3.9
License-File: LICENSE
Requires-Dist: torch (>=2.5.0)
Requires-Dist: torchaudio (>=2.5.0)
Requires-Dist: transformers (>=4.47.1)
Requires-Dist: scipy (>=1.11.4)
Requires-Dist: huggingface-hub (>=0.26.3)
